[{"id":"initialBlockId","type":"paragraph","props":{"textColor":"default","backgroundColor":"default","textAlignment":"left"},"content":[{"type":"text","text":" - zielony","styles":{}}],"children":[]},{"id":"79c752d3-014f-4d8a-8532-e281626ca051","type":"paragraph","props":{"textColor":"default","backgroundColor":"default","textAlignment":"left"},"content":[],"children":[]},{"id":"5c4f631a-754b-4305-8da8-88dd4b735439","type":"paragraph","props":{"textColor":"default","backgroundColor":"default","textAlignment":"left"},"content":[],"children":[]},{"id":"af9cbeee-d992-4216-adf1-e4ed0cdd8da0","type":"paragraph","props":{"textColor":"default","backgroundColor":"default","textAlignment":"left"},"content":[],"children":[]}]